i18ndude/__init__.py
i18ndude/catalog.py
i18ndude/common.py
i18ndude/extract.py
i18ndude/generator.py
i18ndude/gsextract.py
i18ndude/interfaces.py
i18ndude/messages.pot
i18ndude/pygettext.py
i18ndude/script.py
i18ndude/untranslated.py
i18ndude/utils.py
i18ndude/visualisation.py
i18ndude/zcmlextract.py
i18ndude/testdata/input/chameleon.pt
i18ndude/testdata/input/empty-en.po
i18ndude/testdata/input/synctest-de.po
i18ndude/testdata/input/synctest.pot
i18ndude/testdata/input/test-en.po
i18ndude/testdata/input/test.xml
i18ndude/testdata/input/test.zcml
i18ndude/testdata/input/test1.pt
i18ndude/testdata/input/test2-en.po
i18ndude/testdata/input/test2.py
i18ndude/testdata/input/test2_expected-en.po
i18ndude/testdata/input/test3.pt
i18ndude/testdata/input/test4.pt
i18ndude/testdata/input/test5.pt
i18ndude/testdata/output/README.txt
i18ndude/tests/__init__.py
i18ndude/tests/test_catalog.py
i18ndude/tests/test_extract.py
i18ndude/tests/test_untranslated.py
i18ndude/tests/test_utils.py
i18ndude/tests/tox-check-i18ndude-command.sh
i18ndude/tests/utils.py
i18ndude-6.2.1.dist-info/METADATA
i18ndude-6.2.1.dist-info/WHEEL
i18ndude-6.2.1.dist-info/entry_points.txt
i18ndude-6.2.1.dist-info/top_level.txt
i18ndude-6.2.1.dist-info/RECORD
