Metadata-Version: 2.1
Name: i18ndude
Version: 6.2.1
Summary: i18ndude performs various tasks related to ZPT's, Python Scripts and i18n.
Home-page: https://github.com/collective/i18ndude
Author: Daniel Nouri
Author-email: plone-i18n@lists.sourceforge.net
Maintainer: Maurits van Rees
Maintainer-email: maurits@vanrees.org
License: GPL
Keywords: Plone i18n zpt
Classifier: Development Status :: 5 - Production/Stable
Classifier: Environment :: Console
Classifier: License :: OSI Approved :: GNU General Public License (GPL)
Classifier: Operating System :: OS Independent
Classifier: Programming Language :: Python
Classifier: Programming Language :: Python :: 3
Classifier: Programming Language :: Python :: 3.8
Classifier: Programming Language :: Python :: 3.9
Classifier: Programming Language :: Python :: 3.10
Classifier: Programming Language :: Python :: 3.11
Classifier: Programming Language :: Python :: 3.12
Classifier: Programming Language :: Python :: Implementation
Classifier: Programming Language :: Python :: Implementation :: CPython
Classifier: Programming Language :: Python :: Implementation :: PyPy
Classifier: Topic :: Utilities
Requires-Python: >=3.8
Requires-Dist: lxml
Requires-Dist: zope.i18nmessageid >=3.3
Requires-Dist: zope.interface >=3.3
Requires-Dist: zope.tal >=4.3.0
Provides-Extra: plone
Requires-Dist: plone.i18n ; extra == 'plone'
